[
  {
    "date": "2025-07-22",
    "manifest_time": "10:00",
    "carrier": "AUP International for NZ",
    "user": "john.doe",
    "reason": "",
    "timestamp": "2025-07-22T10:05:30"
  },
  {
    "date": "2025-07-22",
    "manifest_time": "10:00",
    "carrier": "Australia Post Metro",
    "user": "jane.smith",
    "reason": "Done Late",
    "timestamp": "2025-07-22T10:35:15"
  },
  {
    "date": "2025-07-22",
    "manifest_time": "11:00",
    "carrier": "EParcel Postplus",
    "user": "bob.wilson",
    "reason": "",
    "timestamp": "2025-07-22T11:02:45"
  },
  {
    "date": "2025-07-23",
    "manifest_time": "00:02",
    "carrier": "Australia Post Metro",
    "user": "Rohan",
    "reason": "",
    "timestamp": "2025-07-23T16:06:31.449936"
  },
  {
    "date": "2025-07-23",
    "manifest_time": "00:02",
    "carrier": "EParcel Express",
    "user": "Rohan",
    "reason": "",
    "timestamp": "2025-07-23T16:06:32.761003"
  },
  {
    "date": "2025-07-23",
    "manifest_time": "00:02",
    "carrier": "EParcel Postplus",
    "user": "Rohan",
    "reason": "",
    "timestamp": "2025-07-23T16:06:33.427899"
  },
  {
    "date": "2025-07-23",
    "manifest_time": "11:02",
    "carrier": "AUP International for NZ",
    "user": "Rohan",
    "reason": "",
    "timestamp": "2025-07-23T16:06:46.609218"
  },
  {
    "date": "2025-07-23",
    "manifest_time": "11:02",
    "carrier": "Australia Post Metro",
    "user": "Rohan",
    "reason": "",
    "timestamp": "2025-07-23T16:06:46.609218"
  },
  {
    "date": "2025-07-23",
    "manifest_time": "11:02",
    "carrier": "EParcel Postplus",
    "user": "Rohan",
    "reason": "",
    "timestamp": "2025-07-23T16:06:46.609218"
  },
  {
    "date": "2025-07-23",
    "manifest_time": "12:32",
    "carrier": "EParcel Express",
    "user": "Rohan",
    "reason": "",
    "timestamp": "2025-07-23T16:06:51.949951"
  },
  {
    "date": "2025-07-23",
    "manifest_time": "13:47",
    "carrier": "NZ Post DPK International",
    "user": "Rohan",
    "reason": "",
    "timestamp": "2025-07-23T16:06:56.904130"
  },
  {
    "date": "2025-07-23",
    "manifest_time": "13:47",
    "carrier": "AUP Oversize Parcel",
    "user": "Rohan",
    "reason": "",
    "timestamp": "2025-07-23T16:06:56.904130"
  },
  {
    "date": "2025-07-23",
    "manifest_time": "13:47",
    "carrier": "DHL Express",
    "user": "Rohan",
    "reason": "",
    "timestamp": "2025-07-23T16:06:56.904130"
  },
  {
    "date": "2025-07-23",
    "manifest_time": "14:32",
    "carrier": "AUP Oversize Parcel",
    "user": "Rohan",
    "reason": "",
    "timestamp": "2025-07-23T16:06:58.542558"
  },
  {
    "date": "2025-07-23",
    "manifest_time": "14:32",
    "carrier": "DHL Express",
    "user": "Rohan",
    "reason": "",
    "timestamp": "2025-07-23T16:06:58.542558"
  },
  {
    "date": "2025-07-23",
    "manifest_time": "15:32",
    "carrier": "Keep at plant",
    "user": "Rohan",
    "reason": "",
    "timestamp": "2025-07-23T16:06:59.800469"
  },
  {
    "date": "2025-07-23",
    "manifest_time": "15:32",
    "carrier": "Toll Api",
    "user": "Rohan",
    "reason": "",
    "timestamp": "2025-07-23T16:06:59.800469"
  },
  {
    "date": "2025-07-23",
    "manifest_time": "15:32",
    "carrier": "Toll Priority",
    "user": "Rohan",
    "reason": "",
    "timestamp": "2025-07-23T16:06:59.800469"
  },
  {
    "date": "2025-07-23",
    "manifest_time": "16:02",
    "carrier": "AUP International Zone 3",
    "user": "Rohan",
    "reason": "",
    "timestamp": "2025-07-23T16:07:03.794416"
  },
  {
    "date": "2025-07-23",
    "manifest_time": "16:02",
    "carrier": "Australia Post Metro",
    "user": "Rohan",
    "reason": "",
    "timestamp": "2025-07-23T16:07:03.794416"
  },
  {
    "date": "2025-07-23",
    "manifest_time": "16:02",
    "carrier": "EParcel Postlus",
    "user": "Rohan",
    "reason": "",
    "timestamp": "2025-07-23T16:07:03.794416"
  }
]